tavosPy/__init__.py
tavosPy-0.5.dist-info/LICENSE
tavosPy-0.5.dist-info/METADATA
tavosPy-0.5.dist-info/WHEEL
tavosPy-0.5.dist-info/top_level.txt
tavosPy-0.5.dist-info/RECORD
