Metadata-Version: 2.1
Name: tavosPy
Version: 0.5
Summary: Processes water outages from Tavos and provides them in a object with proper types
Home-page: https://github.com/JurajNyiri/tavosPy
Author: Juraj Nyíri
Author-email: juraj.nyiri@gmail.com
License: UNKNOWN
Platform: UNKNOWN
Classifier: Programming Language :: Python :: 3
Classifier: License :: OSI Approved :: MIT License
Classifier: Operating System :: OS Independent
License-File: LICENSE
Requires-Dist: requests
Requires-Dist: pyquery
